cartesio/__init__.py
cartesio/cli.py
cartesio/bbox/__init__.py
cartesio/bbox/_iou_helper.py
cartesio/bbox/_nms_helper.py
cartesio/bbox/area.py
cartesio/bbox/iou.py
cartesio/bbox/nms.py
cartesio/bbox/utils.py
cartesio/core/__init__.py
cartesio/core/exceptions.py
cartesio/core/jit_compile.py
cartesio-0.3.0.dist-info/AUTHORS.rst
cartesio-0.3.0.dist-info/LICENSE
cartesio-0.3.0.dist-info/METADATA
cartesio-0.3.0.dist-info/WHEEL
cartesio-0.3.0.dist-info/entry_points.txt
cartesio-0.3.0.dist-info/top_level.txt
cartesio-0.3.0.dist-info/RECORD
