Metadata-Version: 2.1
Name: cartesio
Version: 0.3.0
Summary: Simple geometry accelerated with Numba
Home-page: https://github.com/cdeldon/cartesio
Author: Carlo Del Don
Author-email: carlo.deldon@gmail.com
License: MIT license
Keywords: cartesio
Platform: UNKNOWN
Classifier: Development Status :: 2 - Pre-Alpha
Classifier: Intended Audience :: Developers
Classifier: License :: OSI Approved :: MIT License
Classifier: Natural Language :: English
Classifier: Programming Language :: Python :: 3.6
Classifier: Programming Language :: Python :: 3.7
Classifier: Programming Language :: Python :: 3.8
Requires-Python: >=3.6
Requires-Dist: numba (==0.50.1)
Requires-Dist: numpy (==1.19.0)
Requires-Dist: perfplot (==0.8.5)
